docs/CHANGELOG.md
httprunner/README.md
httprunner/__init__.py
httprunner/__main__.py
httprunner/builtin/__init__.py
httprunner/builtin/comparators.py
httprunner/builtin/functions.py
httprunner/cli.py
httprunner/cli_test.py
httprunner/client.py
httprunner/client_test.py
httprunner/compat.py
httprunner/compat_test.py
httprunner/config.py
httprunner/database/engine.py
httprunner/exceptions.py
httprunner/ext/__init__.py
httprunner/ext/uploader/__init__.py
httprunner/loader.py
httprunner/loader_test.py
httprunner/make.py
httprunner/make_test.py
httprunner/models.py
httprunner/parser.py
httprunner/parser_test.py
httprunner/response.py
httprunner/response_test.py
httprunner/runner.py
httprunner/step.py
httprunner/step_request.py
httprunner/step_request_test.py
httprunner/step_sql_request.py
httprunner/step_testcase.py
httprunner/step_testcase_test.py
httprunner/step_thrift_request.py
httprunner/thrift/data_convertor.py
httprunner/thrift/thrift_client.py
httprunner/utils.py
httprunner/utils_test.py
httprunner-4.3.5.dist-info/LICENSE
httprunner-4.3.5.dist-info/METADATA
httprunner-4.3.5.dist-info/WHEEL
httprunner-4.3.5.dist-info/entry_points.txt
httprunner-4.3.5.dist-info/RECORD
