Metadata-Version: 2.1
Name: httprunner
Version: 4.3.5
Summary: One-stop solution for HTTP(S) testing.
Home-page: https://httprunner.com
License: Apache-2.0
Keywords: HTTP,apitest,perftest,requests
Author: debugtalk
Author-email: debugtalk@gmail.com
Requires-Python: >=3.7,<4.0
Classifier: Development Status :: 5 - Production/Stable
Classifier: License :: OSI Approved :: Apache Software License
Classifier: Operating System :: MacOS
Classifier: Operating System :: Microsoft :: Windows
Classifier: Operating System :: POSIX :: Linux
Classifier: Programming Language :: Python :: 3
Classifier: Programming Language :: Python :: 3.7
Classifier: Programming Language :: Python :: 3.8
Classifier: Programming Language :: Python :: 3.9
Classifier: Programming Language :: Python :: 3.10
Classifier: Programming Language :: Python :: 3.11
Classifier: Topic :: Software Development :: Libraries :: Python Modules
Classifier: Topic :: Software Development :: Quality Assurance
Classifier: Topic :: Software Development :: Testing
Provides-Extra: allure
Provides-Extra: sql
Provides-Extra: thrift
Provides-Extra: upload
Requires-Dist: Brotli (>=1.0.9,<2.0.0)
Requires-Dist: allure-pytest (>=2.8.16,<3.0.0) ; extra == "allure"
Requires-Dist: black (>=22.3.0,<23.0.0)
Requires-Dist: cython (>=0.29.28,<0.30.0) ; extra == "thrift"
Requires-Dist: filetype (>=1.0.7,<2.0.0) ; extra == "upload"
Requires-Dist: jinja2 (>=3.0.3,<4.0.0)
Requires-Dist: jmespath (>=0.9.5,<0.10.0)
Requires-Dist: loguru (>=0.4.1,<0.5.0)
Requires-Dist: pydantic (>=1.8,<1.9)
Requires-Dist: pymysql (>=1.0.2,<2.0.0) ; extra == "sql"
Requires-Dist: pytest (>=7.1.1,<8.0.0)
Requires-Dist: pytest-html (>=3.1.1,<4.0.0)
Requires-Dist: pyyaml (>=6.0.1,<7.0.0)
Requires-Dist: requests (>=2.31.0,<3.0.0)
Requires-Dist: requests-toolbelt (>=0.10.1,<0.11.0) ; extra == "upload"
Requires-Dist: sentry-sdk (>=0.14.4,<0.15.0)
Requires-Dist: sqlalchemy (>=1.4.36,<2.0.0) ; extra == "sql"
Requires-Dist: thrift (>=0.16.0,<0.17.0) ; extra == "thrift"
Requires-Dist: thriftpy2 (>=0.4.14,<0.5.0) ; extra == "thrift"
Requires-Dist: toml (>=0.10.2,<0.11.0)
Requires-Dist: urllib3 (>=1.26,<2.0)
Project-URL: Documentation, https://httprunner.com/docs
Project-URL: Repository, https://github.com/httprunner/httprunner
